{
  "id": "billing",
  "type": "sequence",
  "steps": [
    {
      "id": "profile",
      "subScenario":"profile"      
    },
    {    
      "id":"firstTime",
      "subScenario": "steps/firstTime"
    },
    {      
        "id": "billNumber",
        "type": "prompt",
        "data": { 
            "type":"number", "text":"What is the bill number being complained for non-receipt?" 
        }
    },
    {    
        "id":"checkBillProof",
        "subScenario": "steps/checkBillProof"
    }
  ],
  "models": []
}
